geostat_api/__init__.py
geostat_api/__main__.py
geostat_api/api.py
geostat_api/client.py
geostat_api/feature_provider.py
geostat_api/update_api.py
geostat_api/processes/__init__.py
geostat_api/processes/util.py
geostat_api/processes/variogram.py
geostat_api-0.1.0.dist-info/LICENSE
geostat_api-0.1.0.dist-info/METADATA
geostat_api-0.1.0.dist-info/WHEEL
geostat_api-0.1.0.dist-info/top_level.txt
geostat_api-0.1.0.dist-info/RECORD
