Metadata-Version: 2.1
Name: geostat-api
Version: 0.1.0
Summary: A OGC api compliant REST API for geostatistical applications by hydrocode
Author: Mirko Mälicke
Author-email: mirko@hydrocode.de
License: GPLv3
License-File: LICENSE
Requires-Dist: pygeoapi
Requires-Dist: skgstat-uncertainty
Requires-Dist: requests
Requires-Dist: pyyaml
Requires-Dist: fire
Requires-Dist: shapely
Requires-Dist: flask-cors
Requires-Dist: jinja2 (==3.0.3)
